AUTHORS.rst
CONTRIBUTING.rst
HISTORY.rst
LICENSE
MANIFEST.in
README.rst
setup.py
django_icelandic_addresses.egg-info/PKG-INFO
django_icelandic_addresses.egg-info/SOURCES.txt
django_icelandic_addresses.egg-info/dependency_links.txt
django_icelandic_addresses.egg-info/not-zip-safe
django_icelandic_addresses.egg-info/top_level.txt
ice_addresses/__init__.py
ice_addresses/geo.py
ice_addresses/models.py
ice_addresses/tests.py
ice_addresses/utils.py
ice_addresses/data/Stadfangaskra_20130326.dsv
ice_addresses/importers/__init__.py
ice_addresses/importers/csv.py
ice_addresses/management/__init__.py
ice_addresses/management/commands/__init__.py
ice_addresses/management/commands/import_ice_addresses.py
ice_addresses/migrations/0001_initial.py
ice_addresses/migrations/__init__.py