Metadata-Version: 1.0
Name: django-icelandic-addresses
Version: 0.1.5
Summary: Django app containing a list of Icelandic addresses
Home-page: https://github.com/StefanKjartansson/django-icelandic-addresses
Author: Stefán Kjartansson
Author-email: esteban.supreme@gmail.com
License: BSD
Platform: any
Classifier: Development Status :: 2 - Pre-Alpha
Classifier: Framework :: Django
Classifier: Operating System :: OS Independent
Classifier: Programming Language :: Python
Classifier: Intended Audience :: Developers
Classifier: License :: OSI Approved :: BSD License
Classifier: Operating System :: POSIX
Classifier: Topic :: Software Development :: Libraries :: Python Modules
Classifier: Programming Language :: Python
Classifier: Programming Language :: Python :: 2
Classifier: Programming Language :: Python :: 2.7
Classifier: Programming Language :: Python :: 3
Classifier: Programming Language :: Python :: 3.3
